metovhooks/__init__.py
metovhooks/protect_branch.py
metovhooks/require_version_bump.py
metovhooks-0.1.8.dist-info/LICENSE
metovhooks-0.1.8.dist-info/METADATA
metovhooks-0.1.8.dist-info/WHEEL
metovhooks-0.1.8.dist-info/entry_points.txt
metovhooks-0.1.8.dist-info/top_level.txt
metovhooks-0.1.8.dist-info/RECORD
