Metadata-Version: 2.1
Name: metovhooks
Version: 0.1.8
Summary: My personal git hooks.
Home-page: https://github.com/metov/metovhooks
Author: Azat Akhmetov
Author-email: azatinfo@yandex.com
License: UNKNOWN
Platform: UNKNOWN
Classifier: Programming Language :: Python :: 3
Classifier: Development Status :: 3 - Alpha
Classifier: License :: OSI Approved :: MIT License
License-File: LICENSE
Requires-Dist: coloredlogs
Requires-Dist: docopt
Requires-Dist: GitPython
Requires-Dist: packaging
Requires-Dist: pre-commit-hooks
Requires-Dist: toml
